cosmicpi_server/__init__.py
cosmicpi_server/cli.py
cosmicpi_server/cosmicpi_server.py
cosmicpi_server-0.1.0.dist-info/DESCRIPTION.rst
cosmicpi_server-0.1.0.dist-info/METADATA
cosmicpi_server-0.1.0.dist-info/RECORD
cosmicpi_server-0.1.0.dist-info/WHEEL
cosmicpi_server-0.1.0.dist-info/entry_points.txt
cosmicpi_server-0.1.0.dist-info/metadata.json
cosmicpi_server-0.1.0.dist-info/top_level.txt
